pynipe/__init__.py
pynipe/core/__init__.py
pynipe/core/context.py
pynipe/core/task.py
pynipe/core/thread_local.py
pynipe/core/workflow.py
pynipe/executors/__init__.py
pynipe/executors/base.py
pynipe/executors/local.py
pynipe/executors/serial.py
pynipe/utils/__init__.py
pynipe/utils/proxy.py
pynipe/visualization/__init__.py
pynipe/visualization/graph.py
pynipe-0.1.0.dist-info/METADATA
pynipe-0.1.0.dist-info/WHEEL
pynipe-0.1.0.dist-info/licenses/LICENSE
pynipe-0.1.0.dist-info/RECORD
