Metadata-Version: 2.4
Name: pynipe
Version: 0.1.0
Summary: A neuroimaging workflow library that builds upon Nipype's interfaces
Author-email: Andrew Van <andrew.van@turingmedical.com>
License-File: LICENSE
Requires-Python: >=3.10
Requires-Dist: concurrent-log-handler>=0.9.25
Requires-Dist: networkx>=3.4.2
Requires-Dist: nipype>=1.10.0
Requires-Dist: numpy>=2.2.5
Requires-Dist: rich>=14.0.0
Provides-Extra: dev
Requires-Dist: black>=25.1.0; extra == 'dev'
Requires-Dist: hatch-vcs>=0.3.0; extra == 'dev'
Requires-Dist: isort>=6.0.1; extra == 'dev'
Requires-Dist: pre-commit>=3.6.0; extra == 'dev'
Requires-Dist: pytest-cov>=6.1.1; extra == 'dev'
Requires-Dist: pytest>=8.3.5; extra == 'dev'
Requires-Dist: ruff>=0.11.6; extra == 'dev'
Provides-Extra: visualization
Requires-Dist: matplotlib>=3.10.1; extra == 'visualization'
Requires-Dist: plotly>=6.0.1; extra == 'visualization'
